caqtus_devices/ni6738_analog_card/__init__.py
caqtus_devices/ni6738_analog_card/_compiler.py
caqtus_devices/ni6738_analog_card/_extension.py
caqtus_devices/ni6738_analog_card/py.typed
caqtus_devices/ni6738_analog_card/configuration/__init__.py
caqtus_devices/ni6738_analog_card/configuration/configuration.py
caqtus_devices/ni6738_analog_card/configuration_editor/__init__.py
caqtus_devices/ni6738_analog_card/configuration_editor/editor.py
caqtus_devices/ni6738_analog_card/runtime/__init__.py
caqtus_devices/ni6738_analog_card/runtime/runtime.py
caqtus_devices_ni6738_analog_card-1.13.0.dist-info/METADATA
caqtus_devices_ni6738_analog_card-1.13.0.dist-info/WHEEL
caqtus_devices_ni6738_analog_card-1.13.0.dist-info/licenses/license.md
caqtus_devices_ni6738_analog_card-1.13.0.dist-info/RECORD
